serve_quik/__init__.py
serve_quik/api.py
serve_quik/arg.py
serve_quik/container.py
serve_quik/mar.py
serve_quik/utils.py
serve_quik/tests/__init__.py
serve_quik/tests/conftest.py
serve_quik/tests/test_api.py
serve_quik/tests/test_arg.py
serve_quik-0.0.2.dist-info/METADATA
serve_quik-0.0.2.dist-info/WHEEL
serve_quik-0.0.2.dist-info/top_level.txt
serve_quik-0.0.2.dist-info/RECORD
