Metadata-Version: 2.1
Name: serve-quik
Version: 0.0.2
Summary: functions to make working with TorchServe quik-er
Home-page: https://github.com/donchesworth/serve-quik
Author: Don Chesworth
Author-email: donald.chesworth@gmail.com
License: BSD
Platform: UNKNOWN
Classifier: License :: OSI Approved :: BSD License
Classifier: Programming Language :: Python :: 3.8
Requires-Dist: hugging-quik
Requires-Dist: torchserve
Requires-Dist: torch-model-archiver
Requires-Dist: ruamel.yaml
